wavetools/__init__.py
wavetools/WaveAnalyzers/.gitignore
wavetools/WaveAnalyzers/WaveAnalyzers.py
wavetools/WaveAnalyzers/__init__.py
wavetools/WaveAnalyzers/examples/.gitignore
wavetools/WaveAnalyzers/examples/__init__.py
wavetools/WaveAnalyzers/examples/wa_example.py
wavetools/WaveAnalyzers/examples/wa_gui.py
wavetools/WaveAnalyzers/tests/.gitignore
wavetools/WaveAnalyzers/tests/test_waveanalyzer_api_device_in_loop.py
wavetools/_WaveShapers/WaveShaperAPIs.py
wavetools/_WaveShapers/examples/ws_examples.py
wavetools/_WaveShapers/tests/test_waveshaper_api_device_in_loop.py
wavetools-0.0.3.dist-info/METADATA
wavetools-0.0.3.dist-info/WHEEL
wavetools-0.0.3.dist-info/licenses/LICENSE
wavetools-0.0.3.dist-info/RECORD
