Metadata-Version: 2.4
Name: wavetools
Version: 0.0.3
Summary: Python drivers for Coherent optical instruments. Currently supported devices: WaveAnalyzer (1500S, 200A, 400A, 1500B);(Not Implemented) WaveShaper ;(Not Implemented) WaveMaker 
Project-URL: HomePage, https://www.coherent.com/networking/optical-instrumentation
Project-URL: Documentation, https://oigfinisar.github.io/wavetools_docs/
Author-email: Optical Instrument Group <wavedev@finisar.com>
License-File: LICENSE
Requires-Python: >=3.8
Requires-Dist: httpx
Requires-Dist: numpy
Requires-Dist: pydantic
Provides-Extra: build
Requires-Dist: autoapi; extra == 'build'
Requires-Dist: markdown; extra == 'build'
Requires-Dist: myst-parser; extra == 'build'
Requires-Dist: sphinx; extra == 'build'
Requires-Dist: sphinx-autoapi; extra == 'build'
Requires-Dist: sphinx-design; extra == 'build'
Requires-Dist: twine; extra == 'build'
Provides-Extra: gui
Requires-Dist: pyqt5; extra == 'gui'
Requires-Dist: pyqtgraph; extra == 'gui'
Requires-Dist: scipy; extra == 'gui'
Provides-Extra: test
Requires-Dist: pytest; extra == 'test'
